{
    "analysisType" : "all",

    "savepath" : "/home/universe/c1838736/Cosmic_Rays/V3-1/",

    "saveParams" : ["T","R","n_H","rho_rhomean","B","vrad","gz","L","P_CR","PCR_Pthermal","P_kinetic","P_thermal","P_magnetic","Pthermal_Pmagnetic","gah","Grad_T","Grad_n_H","Grad_bfld","Grad_P_CR","tcool","tff","tcool_tff"],

    "saveEssentials" : ["halo","subhalo","Redshift","Lookback","Snap","type","mass","pos","vol","Rvir","gima","age"],

    "snapMin" : 100,

    "snapMax" : 104,

    "percentiles" :  [15.87, 50.0, 84.13],

    "Rinner" : 25.0,

    "Router" : 175.0,

    "nRbins" : 5,

    "xParam" : "R",

    "NxParamBins" : 100,

    "Axes" : [2,0],

    "zAxis" : [1],

    "QuadPlotBool" : false,

    "numThreads" : 8,

    "boxsize" : 400.0,

    "boxlos" : 50.0,

    "pixres" : 0.20,

    "pixreslos" : 4.0,

    "HaloID" : 0,

    "DPI" : 150,

    "xsize" : 4.0,

    "ysize" : 4.0,

    "colourmapMain" : "plasma",

    "titleBool" : false,

    "fontsize" : 13,

    "fontsizeTitle" : 14,

    "logParameters" : ["dens","ndens","rho_rhomean","csound","T","n_H","B","gz","L","P_thermal","P_magnetic","P_kinetic","P_tot","Pthermal_Pmagnetic", "P_CR", "PCR_Pthermal","gah","bfld","Grad_T","Grad_n_H","Grad_bfld","Grad_P_CR","tcool","theat","tcross","tff","tcool_tff","mass"],

    "nonMassWeightDict" :
      {
      "mass" : "vol",
      "n_H": "vol",
      "ndens": "vol",
      "dens": "vol",
      "rho_rhomean": "vol",
      "B": "vol",
      "bfld" : "vol",
      "P_kinetic": "vol",
      "P_thermal": "vol",
      "P_magnetic": "vol",
      "P_tot": "vol",
      "Pthermal_Pmagnetic": "vol",
      "P_CR" : "vol",
      "PCR_Pthermal" : "vol",
      "gah" : "vol",
      "Grad_T" : "mass",
      "Grad_n_H" : "vol",
      "Grad_bfld" : "vol",
      "Grad_P_CR" : "vol"
      }

}
